odoo8_addon_project_stage_state-8.0.1.1.0.99.dev24-py3.8-nspkg.pth
odoo_addons/project_stage_state/README.rst
odoo_addons/project_stage_state/__init__.py
odoo_addons/project_stage_state/__openerp__.py
odoo_addons/project_stage_state/project.py
odoo_addons/project_stage_state/project_task_type_data.xml
odoo_addons/project_stage_state/project_view.xml
odoo_addons/project_stage_state/i18n/ar.po
odoo_addons/project_stage_state/i18n/bg.po
odoo_addons/project_stage_state/i18n/ca.po
odoo_addons/project_stage_state/i18n/cs.po
odoo_addons/project_stage_state/i18n/da.po
odoo_addons/project_stage_state/i18n/de.po
odoo_addons/project_stage_state/i18n/el.po
odoo_addons/project_stage_state/i18n/es.po
odoo_addons/project_stage_state/i18n/es_CR.po
odoo_addons/project_stage_state/i18n/es_ES.po
odoo_addons/project_stage_state/i18n/es_MX.po
odoo_addons/project_stage_state/i18n/es_VE.po
odoo_addons/project_stage_state/i18n/fi.po
odoo_addons/project_stage_state/i18n/fr.po
odoo_addons/project_stage_state/i18n/fr_CH.po
odoo_addons/project_stage_state/i18n/gl.po
odoo_addons/project_stage_state/i18n/hr.po
odoo_addons/project_stage_state/i18n/hr_HR.po
odoo_addons/project_stage_state/i18n/hu.po
odoo_addons/project_stage_state/i18n/id.po
odoo_addons/project_stage_state/i18n/it.po
odoo_addons/project_stage_state/i18n/ja.po
odoo_addons/project_stage_state/i18n/lt.po
odoo_addons/project_stage_state/i18n/lv.po
odoo_addons/project_stage_state/i18n/mk.po
odoo_addons/project_stage_state/i18n/mn.po
odoo_addons/project_stage_state/i18n/nb.po
odoo_addons/project_stage_state/i18n/nb_NO.po
odoo_addons/project_stage_state/i18n/nl.po
odoo_addons/project_stage_state/i18n/nl_NL.po
odoo_addons/project_stage_state/i18n/pl.po
odoo_addons/project_stage_state/i18n/project_stage_state.pot
odoo_addons/project_stage_state/i18n/pt.po
odoo_addons/project_stage_state/i18n/pt_BR.po
odoo_addons/project_stage_state/i18n/pt_PT.po
odoo_addons/project_stage_state/i18n/ro.po
odoo_addons/project_stage_state/i18n/ru.po
odoo8_addon_project_stage_state-8.0.1.1.0.99.dev24.dist-info/METADATA
odoo8_addon_project_stage_state-8.0.1.1.0.99.dev24.dist-info/WHEEL
odoo8_addon_project_stage_state-8.0.1.1.0.99.dev24.dist-info/namespace_packages.txt
odoo8_addon_project_stage_state-8.0.1.1.0.99.dev24.dist-info/top_level.txt
odoo8_addon_project_stage_state-8.0.1.1.0.99.dev24.dist-info/RECORD
